tsclib-0.1.4.dist-info/METADATA
tsclib-0.1.4.dist-info/WHEEL
tsclib-0.1.4.dist-info/entry_points.txt
tsclib/__init__.py
tsclib/tsclibnet.dll
tsclib-0.1.4.dist-info/RECORD
