Metadata-Version: 2.1
Name: tsclib
Version: 0.1.4
Summary: Python lib for tsclib
Author-Email: Anderson <andersonby@163.com>
License: MIT
Requires-Python: >=3.11
Requires-Dist: pythonnet>=3.0.5
